[
  {
    "id": "prod_001",
    "name": "Ray-Ban Aviator Gold",
    "category": "Frames",
    "brand": "Ray-Ban",
    "model": "RB3025",
    "color": "Gold/Green",
    "size": null,
    "frameWidth": null,
    "bridge": null,
    "temple": null,
    "price": 3500,
    "costPrice": 1800,
    "stock": 12,
    "minStock": 5,
    "supplier": null,
    "supplierPhone": null,
    "lastRestocked": null,
    "sku": "RB-AVI-GG-001",
    "barcode": null,
    "type": "Metal",
    "duration": null,
    "expiryDate": null,
    "description": null,
    "isActive": true,
    "createdAt": "2026-06-11T03:05:55.463Z",
    "updatedAt": "2026-06-13T03:33:14.992Z"
  },
  {
    "id": "prod_002",
    "name": "Ray-Ban Wayfarer Classic",
    "category": "Frames",
    "brand": "Ray-Ban",
    "model": "RB2140",
    "color": "Black",
    "size": null,
    "frameWidth": null,
    "bridge": null,
    "temple": null,
    "price": 3200,
    "costPrice": 1650,
    "stock": 8,
    "minStock": 5,
    "supplier": null,
    "supplierPhone": null,
    "lastRestocked": null,
    "sku": "RB-WAY-BK-001",
    "barcode": null,
    "type": "Acetate",
    "duration": null,
    "expiryDate": null,
    "description": null,
    "isActive": true,
    "createdAt": "2026-06-11T03:05:55.464Z",
    "updatedAt": "2026-06-13T03:33:14.993Z"
  },
  {
    "id": "prod_003",
    "name": "Titan Eye+ Rectangle",
    "category": "Frames",
    "brand": "Titan",
    "model": "TE-1540",
    "color": "Silver/Grey",
    "size": null,
    "frameWidth": null,
    "bridge": null,
    "temple": null,
    "price": 1800,
    "costPrice": 850,
    "stock": 15,
    "minStock": 5,
    "supplier": null,
    "supplierPhone": null,
    "lastRestocked": null,
    "sku": "TT-REC-SG-001",
    "barcode": null,
    "type": "Metal",
    "duration": null,
    "expiryDate": null,
    "description": null,
    "isActive": true,
    "createdAt": "2026-06-11T03:05:55.465Z",
    "updatedAt": "2026-06-13T03:33:14.994Z"
  },
  {
    "id": "prod_004",
    "name": "Fastrack Round Metal",
    "category": "Frames",
    "brand": "Fastrack",
    "model": "FE-2012R",
    "color": "Rose Gold",
    "size": null,
    "frameWidth": null,
    "bridge": null,
    "temple": null,
    "price": 1200,
    "costPrice": 550,
    "stock": 20,
    "minStock": 8,
    "supplier": null,
    "supplierPhone": null,
    "lastRestocked": null,
    "sku": "FT-RND-RG-001",
    "barcode": null,
    "type": "Metal",
    "duration": null,
    "expiryDate": null,
    "description": null,
    "isActive": true,
    "createdAt": "2026-06-11T03:05:55.465Z",
    "updatedAt": "2026-06-13T03:33:14.995Z"
  },
  {
    "id": "prod_005",
    "name": "Oakley Holbrook XL",
    "category": "Frames",
    "brand": "Oakley",
    "model": "OO9417",
    "color": "Matte Black",
    "size": null,
    "frameWidth": null,
    "bridge": null,
    "temple": null,
    "price": 5500,
    "costPrice": 3200,
    "stock": 4,
    "minStock": 5,
    "supplier": null,
    "supplierPhone": null,
    "lastRestocked": null,
    "sku": "OK-HOL-MB-001",
    "barcode": null,
    "type": "Acetate",
    "duration": null,
    "expiryDate": null,
    "description": null,
    "isActive": true,
    "createdAt": "2026-06-11T03:05:55.466Z",
    "updatedAt": "2026-06-13T03:33:14.996Z"
  },
  {
    "id": "prod_006",
    "name": "Vincent Chase FC",
    "category": "Frames",
    "brand": "Vincent Chase",
    "model": "VC-6420",
    "color": "Tortoise",
    "size": null,
    "frameWidth": null,
    "bridge": null,
    "temple": null,
    "price": 950,
    "costPrice": 400,
    "stock": 25,
    "minStock": 10,
    "supplier": null,
    "supplierPhone": null,
    "lastRestocked": null,
    "sku": "VC-FC-TR-001",
    "barcode": null,
    "type": "Acetate",
    "duration": null,
    "expiryDate": null,
    "description": null,
    "isActive": true,
    "createdAt": "2026-06-11T03:05:55.466Z",
    "updatedAt": "2026-06-13T03:33:14.996Z"
  },
  {
    "id": "prod_007",
    "name": "Fastrack Aviator Kids",
    "category": "Frames",
    "brand": "Fastrack",
    "model": "FE-K102",
    "color": "Blue",
    "size": null,
    "frameWidth": null,
    "bridge": null,
    "temple": null,
    "price": 800,
    "costPrice": 350,
    "stock": 2,
    "minStock": 5,
    "supplier": null,
    "supplierPhone": null,
    "lastRestocked": null,
    "sku": "FT-AVI-BL-001",
    "barcode": null,
    "type": "Metal",
    "duration": null,
    "expiryDate": null,
    "description": null,
    "isActive": true,
    "createdAt": "2026-06-11T03:05:55.467Z",
    "updatedAt": "2026-06-13T03:33:14.997Z"
  },
  {
    "id": "prod_008",
    "name": "Titan Rimless Titanium",
    "category": "Frames",
    "brand": "Titan",
    "model": "TE-RM800",
    "color": "Silver",
    "size": null,
    "frameWidth": null,
    "bridge": null,
    "temple": null,
    "price": 4200,
    "costPrice": 2200,
    "stock": 6,
    "minStock": 3,
    "supplier": null,
    "supplierPhone": null,
    "lastRestocked": null,
    "sku": "TT-RM-SI-001",
    "barcode": null,
    "type": "Titanium",
    "duration": null,
    "expiryDate": null,
    "description": null,
    "isActive": true,
    "createdAt": "2026-06-11T03:05:55.467Z",
    "updatedAt": "2026-06-13T03:33:14.998Z"
  },
  {
    "id": "prod_009",
    "name": "Essilor Crizal Easy Pro",
    "category": "Lenses",
    "brand": "Essilor",
    "model": null,
    "color": null,
    "size": null,
    "frameWidth": null,
    "bridge": null,
    "temple": null,
    "price": 2500,
    "costPrice": 1200,
    "stock": 25,
    "minStock": 10,
    "supplier": null,
    "supplierPhone": null,
    "lastRestocked": null,
    "sku": "ES-CEP-001",
    "barcode": null,
    "type": "Blue-cut",
    "duration": null,
    "expiryDate": null,
    "description": null,
    "isActive": true,
    "createdAt": "2026-06-11T03:05:55.468Z",
    "updatedAt": "2026-06-13T03:33:14.998Z"
  },
  {
    "id": "prod_010",
    "name": "Essilor Crizal Forte UV",
    "category": "Lenses",
    "brand": "Essilor",
    "model": null,
    "color": null,
    "size": null,
    "frameWidth": null,
    "bridge": null,
    "temple": null,
    "price": 3200,
    "costPrice": 1600,
    "stock": 18,
    "minStock": 8,
    "supplier": null,
    "supplierPhone": null,
    "lastRestocked": null,
    "sku": "ES-CFU-001",
    "barcode": null,
    "type": "Anti-Reflective",
    "duration": null,
    "expiryDate": null,
    "description": null,
    "isActive": true,
    "createdAt": "2026-06-11T03:05:55.469Z",
    "updatedAt": "2026-06-13T03:33:14.999Z"
  },
  {
    "id": "prod_011",
    "name": "Essilor Varilux Progressive",
    "category": "Lenses",
    "brand": "Essilor",
    "model": null,
    "color": null,
    "size": null,
    "frameWidth": null,
    "bridge": null,
    "temple": null,
    "price": 5500,
    "costPrice": 3000,
    "stock": 10,
    "minStock": 5,
    "supplier": null,
    "supplierPhone": null,
    "lastRestocked": null,
    "sku": "ES-VP-001",
    "barcode": null,
    "type": "Progressive",
    "duration": null,
    "expiryDate": null,
    "description": null,
    "isActive": true,
    "createdAt": "2026-06-11T03:05:55.469Z",
    "updatedAt": "2026-06-13T03:33:15.000Z"
  },
  {
    "id": "prod_012",
    "name": "Zeiss Duravision BlueProtect",
    "category": "Lenses",
    "brand": "Zeiss",
    "model": null,
    "color": null,
    "size": null,
    "frameWidth": null,
    "bridge": null,
    "temple": null,
    "price": 3800,
    "costPrice": 1900,
    "stock": 3,
    "minStock": 5,
    "supplier": null,
    "supplierPhone": null,
    "lastRestocked": null,
    "sku": "ZS-DBP-001",
    "barcode": null,
    "type": "Blue-cut",
    "duration": null,
    "expiryDate": null,
    "description": null,
    "isActive": true,
    "createdAt": "2026-06-11T03:05:55.469Z",
    "updatedAt": "2026-06-13T03:33:15.001Z"
  },
  {
    "id": "prod_013",
    "name": "Zeiss PhotoFusion X",
    "category": "Lenses",
    "brand": "Zeiss",
    "model": null,
    "color": null,
    "size": null,
    "frameWidth": null,
    "bridge": null,
    "temple": null,
    "price": 5200,
    "costPrice": 2800,
    "stock": 7,
    "minStock": 4,
    "supplier": null,
    "supplierPhone": null,
    "lastRestocked": null,
    "sku": "ZS-PFX-001",
    "barcode": null,
    "type": "Photochromic",
    "duration": null,
    "expiryDate": null,
    "description": null,
    "isActive": true,
    "createdAt": "2026-06-11T03:05:55.470Z",
    "updatedAt": "2026-06-13T03:33:15.002Z"
  },
  {
    "id": "prod_014",
    "name": "Kodak Precise Progressive",
    "category": "Lenses",
    "brand": "Kodak",
    "model": null,
    "color": null,
    "size": null,
    "frameWidth": null,
    "bridge": null,
    "temple": null,
    "price": 4200,
    "costPrice": 2100,
    "stock": 9,
    "minStock": 5,
    "supplier": null,
    "supplierPhone": null,
    "lastRestocked": null,
    "sku": "KD-PP-001",
    "barcode": null,
    "type": "Progressive",
    "duration": null,
    "expiryDate": null,
    "description": null,
    "isActive": true,
    "createdAt": "2026-06-11T03:05:55.470Z",
    "updatedAt": "2026-06-13T03:33:15.003Z"
  },
  {
    "id": "prod_015",
    "name": "Essilor Orma 1.50",
    "category": "Lenses",
    "brand": "Essilor",
    "model": null,
    "color": null,
    "size": null,
    "frameWidth": null,
    "bridge": null,
    "temple": null,
    "price": 800,
    "costPrice": 350,
    "stock": 40,
    "minStock": 15,
    "supplier": null,
    "supplierPhone": null,
    "lastRestocked": null,
    "sku": "ES-OR-001",
    "barcode": null,
    "type": "Standard",
    "duration": null,
    "expiryDate": null,
    "description": null,
    "isActive": true,
    "createdAt": "2026-06-11T03:05:55.471Z",
    "updatedAt": "2026-06-13T03:33:15.004Z"
  },
  {
    "id": "prod_016",
    "name": "Zeiss DriveSafe",
    "category": "Lenses",
    "brand": "Zeiss",
    "model": null,
    "color": null,
    "size": null,
    "frameWidth": null,
    "bridge": null,
    "temple": null,
    "price": 4800,
    "costPrice": 2500,
    "stock": 2,
    "minStock": 5,
    "supplier": null,
    "supplierPhone": null,
    "lastRestocked": null,
    "sku": "ZS-DS-001",
    "barcode": null,
    "type": "Anti-Reflective",
    "duration": null,
    "expiryDate": null,
    "description": null,
    "isActive": true,
    "createdAt": "2026-06-11T03:05:55.471Z",
    "updatedAt": "2026-06-13T03:33:15.005Z"
  },
  {
    "id": "prod_017",
    "name": "Bausch+Lomb Ultra",
    "category": "Contact Lenses",
    "brand": "Bausch+Lomb",
    "model": null,
    "color": null,
    "size": null,
    "frameWidth": null,
    "bridge": null,
    "temple": null,
    "price": 1800,
    "costPrice": 900,
    "stock": 15,
    "minStock": 5,
    "supplier": null,
    "supplierPhone": null,
    "lastRestocked": null,
    "sku": "BL-ULT-001",
    "barcode": null,
    "type": "Monthly",
    "duration": "Monthly",
    "expiryDate": null,
    "description": null,
    "isActive": true,
    "createdAt": "2026-06-11T03:05:55.472Z",
    "updatedAt": "2026-06-13T03:33:15.006Z"
  },
  {
    "id": "prod_018",
    "name": "Acuvue Oasys",
    "category": "Contact Lenses",
    "brand": "Acuvue",
    "model": null,
    "color": null,
    "size": null,
    "frameWidth": null,
    "bridge": null,
    "temple": null,
    "price": 1500,
    "costPrice": 750,
    "stock": 20,
    "minStock": 8,
    "supplier": null,
    "supplierPhone": null,
    "lastRestocked": null,
    "sku": "AJ-OAS-001",
    "barcode": null,
    "type": "Bi-weekly",
    "duration": "Bi-weekly",
    "expiryDate": null,
    "description": null,
    "isActive": true,
    "createdAt": "2026-06-11T03:05:55.472Z",
    "updatedAt": "2026-06-13T03:33:15.007Z"
  },
  {
    "id": "prod_019",
    "name": "Acuvue 1-Day Moist",
    "category": "Contact Lenses",
    "brand": "Acuvue",
    "model": null,
    "color": null,
    "size": null,
    "frameWidth": null,
    "bridge": null,
    "temple": null,
    "price": 2200,
    "costPrice": 1100,
    "stock": 12,
    "minStock": 5,
    "supplier": null,
    "supplierPhone": null,
    "lastRestocked": null,
    "sku": "AJ-1DM-001",
    "barcode": null,
    "type": "Daily",
    "duration": "Daily",
    "expiryDate": null,
    "description": null,
    "isActive": true,
    "createdAt": "2026-06-11T03:05:55.473Z",
    "updatedAt": "2026-06-13T03:33:15.008Z"
  },
  {
    "id": "prod_020",
    "name": "Bausch+Lomb SofLens 59",
    "category": "Contact Lenses",
    "brand": "Bausch+Lomb",
    "model": null,
    "color": null,
    "size": null,
    "frameWidth": null,
    "bridge": null,
    "temple": null,
    "price": 650,
    "costPrice": 300,
    "stock": 1,
    "minStock": 5,
    "supplier": null,
    "supplierPhone": null,
    "lastRestocked": null,
    "sku": "BL-SL59-001",
    "barcode": null,
    "type": "Monthly",
    "duration": "Monthly",
    "expiryDate": null,
    "description": null,
    "isActive": true,
    "createdAt": "2026-06-11T03:05:55.473Z",
    "updatedAt": "2026-06-13T03:33:15.009Z"
  },
  {
    "id": "prod_021",
    "name": "Titan Sunglass Polarized",
    "category": "Sunglasses",
    "brand": "Titan",
    "model": "TS-9003",
    "color": "Black/Grey",
    "size": null,
    "frameWidth": null,
    "bridge": null,
    "temple": null,
    "price": 2200,
    "costPrice": 1100,
    "stock": 8,
    "minStock": 3,
    "supplier": null,
    "supplierPhone": null,
    "lastRestocked": null,
    "sku": "TT-SG-BG-001",
    "barcode": null,
    "type": "Polarized",
    "duration": null,
    "expiryDate": null,
    "description": null,
    "isActive": true,
    "createdAt": "2026-06-11T03:05:55.474Z",
    "updatedAt": "2026-06-13T03:33:15.009Z"
  },
  {
    "id": "prod_022",
    "name": "Ray-Ban Clubmaster Classic",
    "category": "Sunglasses",
    "brand": "Ray-Ban",
    "model": "RB3016",
    "color": "Black/Green",
    "size": null,
    "frameWidth": null,
    "bridge": null,
    "temple": null,
    "price": 4800,
    "costPrice": 2600,
    "stock": 5,
    "minStock": 3,
    "supplier": null,
    "supplierPhone": null,
    "lastRestocked": null,
    "sku": "RB-CLB-BG-001",
    "barcode": null,
    "type": "Classic",
    "duration": null,
    "expiryDate": null,
    "description": null,
    "isActive": true,
    "createdAt": "2026-06-11T03:05:55.474Z",
    "updatedAt": "2026-06-13T03:33:15.010Z"
  },
  {
    "id": "prod_023",
    "name": "Fastrack Pento Sunglass",
    "category": "Sunglasses",
    "brand": "Fastrack",
    "model": "FS-P200",
    "color": "Black/Grey",
    "size": null,
    "frameWidth": null,
    "bridge": null,
    "temple": null,
    "price": 1500,
    "costPrice": 700,
    "stock": 10,
    "minStock": 4,
    "supplier": null,
    "supplierPhone": null,
    "lastRestocked": null,
    "sku": "FT-PT-BG-001",
    "barcode": null,
    "type": "Polarized",
    "duration": null,
    "expiryDate": null,
    "description": null,
    "isActive": true,
    "createdAt": "2026-06-11T03:05:55.475Z",
    "updatedAt": "2026-06-13T03:33:15.011Z"
  },
  {
    "id": "prod_024",
    "name": "Oakley Jawbreaker",
    "category": "Sunglasses",
    "brand": "Oakley",
    "model": "OO9290",
    "color": "Matte Black/Prizm",
    "size": null,
    "frameWidth": null,
    "bridge": null,
    "temple": null,
    "price": 9800,
    "costPrice": 5500,
    "stock": 3,
    "minStock": 2,
    "supplier": null,
    "supplierPhone": null,
    "lastRestocked": null,
    "sku": "OK-JB-MP-001",
    "barcode": null,
    "type": "Sports",
    "duration": null,
    "expiryDate": null,
    "description": null,
    "isActive": true,
    "createdAt": "2026-06-11T03:05:55.475Z",
    "updatedAt": "2026-06-13T03:33:15.012Z"
  },
  {
    "id": "prod_025",
    "name": "ReNu MultiPlus 120ml",
    "category": "Solutions",
    "brand": "Bausch+Lomb",
    "model": null,
    "color": null,
    "size": null,
    "frameWidth": null,
    "bridge": null,
    "temple": null,
    "price": 280,
    "costPrice": 140,
    "stock": 30,
    "minStock": 10,
    "supplier": null,
    "supplierPhone": null,
    "lastRestocked": null,
    "sku": "BL-RNU-120",
    "barcode": null,
    "type": "Multipurpose",
    "duration": null,
    "expiryDate": null,
    "description": null,
    "isActive": true,
    "createdAt": "2026-06-11T03:05:55.476Z",
    "updatedAt": "2026-06-13T03:33:15.012Z"
  },
  {
    "id": "prod_026",
    "name": "Opti-Free Puremoist 300ml",
    "category": "Solutions",
    "brand": "Alcon",
    "model": null,
    "color": null,
    "size": null,
    "frameWidth": null,
    "bridge": null,
    "temple": null,
    "price": 350,
    "costPrice": 170,
    "stock": 22,
    "minStock": 8,
    "supplier": null,
    "supplierPhone": null,
    "lastRestocked": null,
    "sku": "AL-OFP-300",
    "barcode": null,
    "type": "Multipurpose",
    "duration": null,
    "expiryDate": null,
    "description": null,
    "isActive": true,
    "createdAt": "2026-06-11T03:05:55.476Z",
    "updatedAt": "2026-06-13T03:33:15.013Z"
  },
  {
    "id": "prod_027",
    "name": "Lens Cleaning Spray 60ml",
    "category": "Accessories",
    "brand": "Generic",
    "model": null,
    "color": null,
    "size": null,
    "frameWidth": null,
    "bridge": null,
    "temple": null,
    "price": 120,
    "costPrice": 40,
    "stock": 50,
    "minStock": 15,
    "supplier": null,
    "supplierPhone": null,
    "lastRestocked": null,
    "sku": "GN-LCS-060",
    "barcode": null,
    "type": "Cleaning",
    "duration": null,
    "expiryDate": null,
    "description": null,
    "isActive": true,
    "createdAt": "2026-06-11T03:05:55.476Z",
    "updatedAt": "2026-06-13T03:33:15.014Z"
  },
  {
    "id": "prod_028",
    "name": "Microfiber Cloth (Pack of 3)",
    "category": "Accessories",
    "brand": "Generic",
    "model": null,
    "color": null,
    "size": null,
    "frameWidth": null,
    "bridge": null,
    "temple": null,
    "price": 150,
    "costPrice": 45,
    "stock": 40,
    "minStock": 15,
    "supplier": null,
    "supplierPhone": null,
    "lastRestocked": null,
    "sku": "GN-MFC-003",
    "barcode": null,
    "type": "Cleaning",
    "duration": null,
    "expiryDate": null,
    "description": null,
    "isActive": true,
    "createdAt": "2026-06-11T03:05:55.477Z",
    "updatedAt": "2026-06-13T03:33:15.014Z"
  }
]
